
{
	"entities" :
	[

		{
			"acc" :
			{
				"x" : 0.0,
				"y" : 0.0
			},
			"color" : "green",
			"mass" : 597200000.0,
			"name" : "earth",
			"pos" :
			{
				"x" : 2.805479070288739e-16,
				"y" : 601.3333333333334
			},
			"radius" : 637100.0,
			"v" :
			{
				"x" : 2.028057159582466e-16,
				"y" : 220.0
			}
		},

		{
			"acc" :
			{
				"x" : 0.0,
				"y" : 0.0
			},
			"color" : "red",
			"mass" : 1000.0,
			"name" : "flab",
			"pos" :
			{
				"x" : 637700.0,
				"y" : 601.3549425193977
			},
			"radius" : 20.0,
			"v" :
			{
				"x" : -2.679151663474234e-13,
				"y" : 220.0079057995645
			}
		},

		{
			"acc" :
			{
				"x" : 0.0,
				"y" : 0.0
			},
			"color" : "yellow",
			"mass" : 100.0,
			"name" : "bab",
			"pos" :
			{
				"x" : 637700.0,
				"y" : 1101.354942519866
			},
			"radius" : 30.0,
			"v" :
			{
				"x" : -2.678996653704821e-13,
				"y" : 220.0079057999027
			}
		},

		{
			"acc" :
			{
				"x" : 0.0,
				"y" : 0.0
			},
			"color" : "purple",
			"mass" : 1000.0,
			"name" : "hab",
			"pos" :
			{
				"x" : 637700.0,
				"y" : 801.3549425197095
			},
			"radius" : 30.0,
			"v" :
			{
				"x" : -2.679044634894183e-13,
				"y" : 220.007905799790
			}
		}
	],
	"habs" :
	[

		{
			"Isp" : 800,
			"acc" :
			{
				"x" : 0.0,
				"y" : 0.0
			},
			"color" : "gray",
			"fuel" : 10000.0,
			"mass" : 450000.0,
			"name" : "Hawking III",
			"pos" :
			{
				"x" : 637700.0,
				"y" : 169.6522222222243
			},
			"radius" : 0.60,
			"thrust" : 600.0,
			"v" :
			{
				"x" : -2.678954754975355e-13,
				"y" : 220.1166666666681
			}
		}
	]
}
